mas_cookie_manager/__init__.py
mas_cookie_manager/mas_cookie_manager.py
mas_cookie_manager/build/main.js
mas_cookie_manager/build/main.js.LICENSE.txt
mas_cookie_manager-0.1.5.dist-info/licenses/LICENSE
mas_cookie_manager-0.1.5.dist-info/METADATA
mas_cookie_manager-0.1.5.dist-info/WHEEL
mas_cookie_manager-0.1.5.dist-info/top_level.txt
mas_cookie_manager-0.1.5.dist-info/RECORD
